<?xml version="1.0" encoding="UTF-8"?>
<!DOCTYPE task PUBLIC "-//OASIS//DTD DITA Task//EN" "http://docs.oasis-open.org/dita/v1.1/OS/dtd/task.dtd">
<task id="taskId">
    <title>View Result Set</title>
    <shortdesc>View a <i>Result Set</i> from a query.</shortdesc>
    <taskbody>
        <context>From a <uicontrol>Results</uicontrol> tab in the <wintitle>Query Project</wintitle>
            window or from the <wintitle>Query History</wintitle> window with a query
            selected:</context>
        <steps>
            <step>
                <cmd>Double-click on a result set.</cmd>
                <stepresult>The <wintitle>Results</wintitle> window will open alongside the session
                    in which the results were found. Each result will be displayed with its
                        <uicontrol>Record #</uicontrol>, <uicontrol>Speaker</uicontrol>,
                        <uicontrol>Result</uicontrol>, and any associated metadata.<note>To open
                        only the <wintitle>Results</wintitle> window, deselect <uicontrol>Open
                            session with result set</uicontrol> before opening a result set.</note>
                    <note>To arrange results by a certain column, click on its header. To reorder
                        columns, click and drag their header to the left or right. To further change
                        column view options, click on the icon to the right of the column
                        headers.</note></stepresult>
            </step>
            <step>
                <cmd>To view a result in the <wintitle>Session Editor</wintitle>, click on it in the
                        <wintitle>Results</wintitle> window.</cmd>
                <stepresult>The record in which the result was found will be displayed, with the
                    result highlighted in the <wintitle>Record Data</wintitle> view.</stepresult>
            </step>
            <step>
                <cmd>To exclude an extraneous result from the list, select it and choose the 
                    <menucascade><uicontrol>Results</uicontrol><uicontrol>Toggle result excluded</uicontrol></menucascade>
                    menu item or press <userinput>Delete/Backspace</userinput>. You can show or hide 
                    excluded results by selecting or deselecting <uicontrol>Show excluded
                    results</uicontrol>.</cmd>
            </step>
            <step>
                <cmd>To save any changes to a result set, click <uicontrol>Save</uicontrol>.</cmd>
            </step>
        </steps>
    </taskbody>
</task>
