<?xml version="1.0" encoding="UTF-8" standalone="no"?>
<opgraph xmlns="http://gedge.ca/ns/opgraph" xmlns:nes="https://www.phon.ca/ns/node_editor" xmlns:oga="http://gedge.ca/ns/opgraph-app" xmlns:ogcn="http://gedge.ca/ns/opgraph-common-nodes" xmlns:opqry="https://phon.ca/ns/opgraph_query" xmlns:qry="http://phon.ling.mun.ca/ns/query">
    <graph id="root">
        <node id="48add314" name="Project" type="class:ca.gedge.opgraph.nodes.reflect.ObjectNode">
            <extensions>
                <oga:settings>
                    <oga:property key="ca.gedge.opgraph.nodes.reflect.ObjectNode.declaredClass"><![CDATA[ca.phon.project.Project]]></oga:property>
                    <oga:property key="contextKey"><![CDATA[_project]]></oga:property>
                </oga:settings>
                <oga:meta x="15" y="15"/>
            </extensions>
        </node>
        <node id="6ffcfb69" name="ArrayList" type="class:ca.gedge.opgraph.nodes.reflect.ObjectNode">
            <extensions>
                <oga:settings>
                    <oga:property key="ca.gedge.opgraph.nodes.reflect.ObjectNode.declaredClass"><![CDATA[java.util.ArrayList]]></oga:property>
                    <oga:property key="contextKey"><![CDATA[_selectedSessions]]></oga:property>
                </oga:settings>
                <oga:meta x="138" y="252"/>
            </extensions>
        </node>
        <ogcn:macro id="95ceb695482449a9" name="Glottalization (all)" type="ca.gedge.opgraph.nodes.general.MacroNode">
            <graph id="637c37c7">
                <opqry:queryNode id="ff2dad4523a741d7" name="Query : Phones" type="ca.phon.app.opgraph.nodes.query.QueryNode">
                    <qry:query xmlns="http://phon.ling.mun.ca/ns/query" date="2016-09-07T11:30:12.739-02:30" name="Phones" uuid="806da9a0-3c28-4cf7-bbf4-4e52a4890399">
                        <script>
                            <url ref="Phones" rel="stock"/>
                            <param id="filters.actualResultFilter.caseSensitive">false</param>
                            <param id="filters.actualResultFilter.exactMatch">true</param>
                            <param id="filters.actualResultFilter.filter">{glottal}</param>
                            <param id="filters.primary.filter">{-glottal}</param>
                            <param id="metadataOptions.pcc_aligned.ignoreDiacritics">false</param>
                            <param id="metadataOptions.pcc_standard.ignoreDiacritics">false</param>
                        </script>
                    </qry:query>
                    <extensions>
                        <oga:settings/>
                        <oga:meta x="298" y="33"/>
                    </extensions>
                </opqry:queryNode>
                <node id="d71a2cdbdf3f4cf8" type="class:ca.phon.app.opgraph.nodes.table.ResultsToTableNode">
                    <extensions>
                        <oga:settings>
                            <oga:property key="includeMetadata"><![CDATA[true]]></oga:property>
                            <oga:property key="includeTierInfo"><![CDATA[true]]></oga:property>
                            <oga:property key="includeSpeakerInfo"><![CDATA[true]]></oga:property>
                            <oga:property key="includeSessionInfo"><![CDATA[true]]></oga:property>
                            <oga:property key="includeExtraColumns"><![CDATA[true]]></oga:property>
                        </oga:settings>
                        <oga:meta x="492" y="33"/>
                    </extensions>
                </node>
                <node id="c3e1b1b7adfa4869" type="class:ca.phon.app.opgraph.nodes.table.InventoryNode">
                    <extensions>
                        <opqry:inventoryoptions>
                            <opqry:column caseSensitive="false" column="Session" ignoreDiacritics="false"/>
                            <opqry:column caseSensitive="false" column="IPA Target" ignoreDiacritics="false"/>
                            <opqry:column caseSensitive="false" column="IPA Actual" ignoreDiacritics="false"/>
                        </opqry:inventoryoptions>
                        <oga:settings/>
                        <oga:meta x="667" y="33"/>
                    </extensions>
                </node>
                <node id="f9b278a9bbba4846" type="class:ca.phon.app.opgraph.nodes.table.SortNode">
                    <extensions>
                        <opqry:sortoptions>
                            <opqry:sortBy column="Session" order="ascending" type="plain"/>
                            <opqry:sortBy column="IPA Target" order="ascending" type="ipa"/>
                            <opqry:sortBy column="IPA Actual" order="ascending" type="ipa"/>
                        </opqry:sortoptions>
                        <oga:settings/>
                        <oga:meta x="298" y="174"/>
                    </extensions>
                </node>
                <node id="f093bc29e0294653" type="class:ca.phon.app.opgraph.nodes.log.PrintBufferNode">
                    <extensions>
                        <oga:settings>
                            <oga:property key="showTable"><![CDATA[true]]></oga:property>
                        </oga:settings>
                        <oga:meta x="473" y="174">
                            <oga:default for="buffer" type="java.lang.String">Glottalization</oga:default>
                        </oga:meta>
                    </extensions>
                </node>
                <link dest="d71a2cdbdf3f4cf8" destField="project" source="ff2dad4523a741d7" sourceField="project"/>
                <link dest="f093bc29e0294653" destField="data" source="f9b278a9bbba4846" sourceField="table"/>
                <link dest="c3e1b1b7adfa4869" destField="table" source="d71a2cdbdf3f4cf8" sourceField="table"/>
                <link dest="d71a2cdbdf3f4cf8" destField="results" source="ff2dad4523a741d7" sourceField="results"/>
                <link dest="f9b278a9bbba4846" destField="table" source="c3e1b1b7adfa4869" sourceField="table"/>
            </graph>
            <ogcn:published_input field="sessions" name="sessions" ref="ff2dad4523a741d7"/>
            <ogcn:published_input field="project" name="project" ref="ff2dad4523a741d7"/>
            <extensions>
                <oga:meta x="321" y="45"/>
            </extensions>
        </ogcn:macro>
        <link dest="95ceb695482449a9" destField="project" source="48add314" sourceField="obj"/>
        <link dest="95ceb695482449a9" destField="sessions" source="6ffcfb69" sourceField="obj"/>
        <extensions>
            <opqry:nodewizard type="ca.phon.app.opgraph.analysis.AnalysisWizardExtension">
                <opqry:info format="markdown" title="Glottalization">
                    <opqry:message># Glottalization

Generate an inventory of `{-glottal}` &amp;#x2194; `{glottal}` alignments found in the selected sessions.

## Output

 - *Session*

   Session name

 - *IPA Target*

   IPA Target phone

 - *IPA Actual*

   IPA Actual phone

 - *Total*

   Number of occurrences in the session.

## Example:

Session|IPA Target|IPA Actual|Total
:---:|:---:|:---:|:---:
Catootje.1_10_10|f|h|1
Catootje.1_10_10|v|h|9
Catootje.1_10_10|v|ɦ|1
Catootje.1_10_10|s|ʔ|1
Catootje.1_10_10|s|h|1
Catootje.1_10_10|s|ɦ|1
Catootje.1_10_10|χ|h|2
Catootje.1_10_10|l|h|1
Catootje.1_10_10|ʋ|ɦ|1
Catootje.1_10_24|f|ɦ|2
Catootje.1_10_24|v|h|5
Catootje.1_10_24|s|ʔ|1
Catootje.1_10_24|s|h|1
Catootje.1_10_24|z|h|3
Catootje.1_10_24|z|ɦ͡j̆|1
Catootje.1_10_24|χ|h|1
Catootje.1_10_24|χ|ɦ|1
Catootje.1_10_24|l|ʔ|1
Catootje.1_10_24|l|h͡j̆|1
Catootje.1_10_24|l|ɦ|2
Catootje.1_10_24|j|h̆|1
Catootje.1_11_09|p|ɦ|1
Catootje.1_11_09|k|h|1
Catootje.1_11_09|k|ɦ|2
Catootje.1_11_09|f|ɦ|1
Catootje.1_11_09|v|h|3
Catootje.1_11_09|v|ɦ|5
Catootje.1_11_09|s|ɦ|1
Catootje.1_11_09|z|h|3
Catootje.1_11_09|χ|h|3
Catootje.1_11_09|χ|ɦ|3
Catootje.1_11_09|n|ɦ|1
Catootje.1_11_09|l|h|2
Catootje.1_11_09|l|ɦ|1
Catootje.1_11_09|ʋ|h|1
Catootje.1_11_09|ʋ|ɦ|1
Catootje.1_11_22|k|ʔ|1
Catootje.1_11_22|f|h|3
Catootje.1_11_22|v|ʔ|1
Catootje.1_11_22|v|h|12
Catootje.1_11_22|s|h|3
Catootje.1_11_22|s|ɦ|1
Catootje.1_11_22|z|h|1
Catootje.1_11_22|χ|h|6
Catootje.1_11_22|m|h|1
Catootje.1_11_22|l|h|3
Catootje.1_11_22|ʀ|h|2
Catootje.1_11_22|ɪ|ʔ|3
Catootje.1_11_22|ə|ʔ|1
Catootje.2_00_06|p|ʔ|1
Catootje.2_00_06|b|ɦ|1
Catootje.2_00_06|t|ɦ|2
Catootje.2_00_06|d|ʔ|1
Catootje.2_00_06|k|ɦ|3
Catootje.2_00_06|f|h|1
Catootje.2_00_06|f|ɦ|7
Catootje.2_00_06|v|h|2
Catootje.2_00_06|v|ɦ|10
Catootje.2_00_06|z|h|1
Catootje.2_00_06|z|ɦ|3
Catootje.2_00_06|ʒ|ɦ|1
Catootje.2_00_06|χ|ʔ|1
Catootje.2_00_06|χ|h|2
Catootje.2_00_06|χ|ɦ|15
Catootje.2_00_06|l|ɦ|7
Catootje.2_00_06|ʀ|ɦ|3
Catootje.2_00_06|ʋ|ɦ|5
Catootje.2_00_06|ʋ|ɦ͡j|1
Catootje.2_00_06|o|ʔ|1
Catootje.2_00_19|f|h|1
Catootje.2_00_19|f|ɦ|1
Catootje.2_00_19|v|ɦ|1
Catootje.2_00_19|z|h|1
Catootje.2_00_19|χ|h|1
Catootje.2_00_19|χ|ɦ|1
Catootje.2_00_19|l|h|1
Catootje.2_00_19|l|ɦ|3
Catootje.2_00_19|ʋ|h|1
Catootje.2_00_19|ʋ|ɦ|4
Catootje.2_01_03|f|h|6
Catootje.2_01_03|v|h|7
Catootje.2_01_03|s|h|1
Catootje.2_01_03|z|h|1
Catootje.2_01_03|ʒ|h|2
Catootje.2_01_03|ʒ|ɦ|1
Catootje.2_01_03|χ|h|14
Catootje.2_01_03|m|h|1
Catootje.2_01_03|n|h|1
Catootje.2_01_03|l|h|3
Catootje.2_01_03|ɹ|ʔ|1
Catootje.2_01_03|ʀ|h|3
Catootje.2_01_03|ʋ|h|1
Catootje.2_01_03|ʋ|h̺|1
Catootje.2_01_03|ɪ|ʔ|1
Catootje.2_01_03|ə|ʔ|1
Catootje.2_02_14|ɡ|ɦ|1
Catootje.2_02_14|f|h|4
Catootje.2_02_14|v|ʔ|1
Catootje.2_02_14|v|h|6
Catootje.2_02_14|s|h|1
Catootje.2_02_14|ʒ|ɦ|1
Catootje.2_02_14|χ|h|4
Catootje.2_02_14|l|h|1
Catootje.2_02_14|ʋ|ʔ|1
Catootje.2_02_14|ʋ|h|1
Catootje.2_02_14|ə|ʔ|1
Catootje.2_02_28|f|h|3
Catootje.2_02_28|f|ɦ|1
Catootje.2_02_28|v|h|8
Catootje.2_02_28|v|h̆|1
Catootje.2_02_28|v|ɦ|1
Catootje.2_02_28|s|ɦ|1
Catootje.2_02_28|χ|h|11
Catootje.2_02_28|χ|ɦ|4
Catootje.2_02_28|l|h|1
Catootje.2_02_28|r|h͡ʀ̣̆|1
Catootje.2_02_28|ʀ|h|4
Catootje.2_02_28|ʀ|hˑ|1
Catootje.2_02_28|ʀ|h͡ʁ̆|1
Catootje.2_02_28|ʀ|h̺|2
Catootje.2_02_28|ʀ|h̺ː|1
Catootje.2_02_28|ʀ|ɦ|1
Catootje.2_02_28|ʋ|h|9
Catootje.2_02_28|ʋ|ɦ|4
Catootje.2_02_28|ə|ʔ|6
Catootje.2_02_28|ə|h|1
Catootje.2_03_25|f|h|6
Catootje.2_03_25|v|h|13
Catootje.2_03_25|z|h|3
Catootje.2_03_25|ʒ|h|1
Catootje.2_03_25|χ|ʔ|1
Catootje.2_03_25|χ|h|41
Catootje.2_03_25|ʋ|h|7
Catootje.2_03_25|ə|ʔ|4
Catootje.2_03_25|ə|h|1
Catootje.2_04_11|t|h|1
Catootje.2_04_11|f|ʔ|1
Catootje.2_04_11|f|h|13
Catootje.2_04_11|v|h|13
Catootje.2_04_11|ʒ|h|1
Catootje.2_04_11|χ|h|41
Catootje.2_04_11|l|ʔ|1
Catootje.2_04_11|l|h|1
Catootje.2_04_11|ʋ|h|9
Catootje.2_04_11|ʋ|h̺|1
Catootje.2_04_11|ə|ʔ|2
Catootje.2_04_25|t|h|1
Catootje.2_04_25|k|ʔ|1
Catootje.2_04_25|f|h|4
Catootje.2_04_25|v|h|7
Catootje.2_04_25|ʃ̟|h|1
Catootje.2_04_25|χ|ʔ|3
Catootje.2_04_25|χ|h|32
Catootje.2_04_25|ʀ|h|1
Catootje.2_04_25|ʋ|ʔ|1
Catootje.2_04_25|ʋ|h|5
Catootje.2_04_25|ʋ|ɦ|1
Catootje.2_04_25|j|h|1
Catootje.2_05_08|f|h|4
Catootje.2_05_08|v|h|9
Catootje.2_05_08|ʒ|h|2
Catootje.2_05_08|χ|h|26
Catootje.2_05_08|ʀ|h|3
Catootje.2_05_08|ʋ|h|2
Catootje.2_05_08|j|h|1
Catootje.2_05_22|p|h|1
Catootje.2_05_22|f|h|6
Catootje.2_05_22|v|h|25
Catootje.2_05_22|s|h|2
Catootje.2_05_22|χ|h|43
Catootje.2_05_22|χ|ɦ|1
Catootje.2_05_22|ɹ|ʔ|2
Catootje.2_05_22|ʀ|h|2
Catootje.2_05_22|ʋ|h|7
Catootje.2_06_06|f|h|3
Catootje.2_06_06|v|h|9
Catootje.2_06_06|χ|h|26
Catootje.2_06_06|χ|h̩|1
Catootje.2_06_06|ʋ|h|2
Catootje.2_07_04|k|h|1
Catootje.2_07_04|v|h|2
Catootje.2_07_04|z|h|1
Catootje.2_07_04|χ|ʔ|1
Catootje.2_07_04|χ|h|24
Catootje.2_07_04|ʋ|h|1
Catootje.1_11_09|l|w|1
Catootje.1_11_09|l|j|1
Catootje.1_11_09|l|u|1
Catootje.1_11_09|ʀ|j|2
Catootje.1_11_09|ʀ|jː|1
Catootje.1_11_09|ʀ|j̆|2
Catootje.1_11_09|ʀ|i|1
Catootje.1_11_22|l|j|2
Catootje.1_11_22|l|u|2
Catootje.1_11_22|l|ɪˑ|1
Catootje.1_11_22|ɹ|a|1
Catootje.1_11_22|ʀ|j|2
Catootje.1_11_22|ʀ|ɪ|1
Catootje.2_00_06|l|j|5
Catootje.2_00_06|l|i|1
Catootje.2_00_06|l|uˑ|1
Catootje.2_00_06|l|ŭ|2
Catootje.2_00_06|l|ɔ|1
Catootje.2_00_06|ɹ|j|1
Catootje.2_00_06|ɹ|ŭ|1
Catootje.2_00_06|ʀ|j|4
Catootje.2_00_06|ʀ|jː|2
Catootje.2_00_19|l|j|6
Catootje.2_00_19|ɹ|ĭ|1
Catootje.2_00_19|ɹ|u|1
Catootje.2_00_19|ʀ|j|8
Catootje.2_01_03|l|j|5
Catootje.2_01_03|l|ŭ|1
Catootje.2_01_03|ɹ|ŭ|1
Catootje.2_01_03|ɹ|ə|1
Catootje.2_01_03|ʀ|j|7
Catootje.2_02_14|l|u|4
Catootje.2_02_14|l|ŭ|1
Catootje.2_02_14|l|u̞|1
Catootje.2_02_14|ɹ|u|13
Catootje.2_02_14|ɹ|uː|1
Catootje.2_02_14|ɹ|ŭ|1
Catootje.2_02_14|ɹ|ə|2
Catootje.2_02_14|ʀ|w|1
Catootje.2_02_28|l|j|1
Catootje.2_02_28|l|jː|1
Catootje.2_02_28|l|ɯ|1
Catootje.2_02_28|l|u|12
Catootje.2_02_28|l|ŭ|2
Catootje.2_02_28|ɹ|ĭ|1
Catootje.2_02_28|ɹ|ʉː|1
Catootje.2_02_28|ɹ|ɯ|1
Catootje.2_02_28|ɹ|u|9
Catootje.2_02_28|ɹ|ŭ|3
Catootje.2_02_28|ʀ|m͡ʋ|1
Catootje.2_02_28|ʀ|ẉː|1
Catootje.2_03_25|l|u|3
Catootje.2_03_25|l|ŭ|4
Catootje.2_03_25|l|ɔ|1
Catootje.2_03_25|ɹ|ï|1
Catootje.2_03_25|ɹ|ĭ|2
Catootje.2_03_25|ɹ|y|1
Catootje.2_03_25|ɹ|ɯ̈|2
Catootje.2_03_25|ɹ|ɯ̆|1
Catootje.2_03_25|ɹ|u|3
Catootje.2_03_25|ɹ|ŭ|3
Catootje.2_03_25|ɹ|ɪ̆|1
Catootje.2_04_11|l|j|2
Catootje.2_04_11|l|ĭ|1
Catootje.2_04_11|l|ɯ̆|1
Catootje.2_04_11|l|u|2
Catootje.2_04_11|l|uˑ|1
Catootje.2_04_11|l|ŭ|1
Catootje.2_04_11|ɹ|ɯ|1
Catootje.2_04_11|ɹ|ɯː|1
Catootje.2_04_11|ɹ|u|1
Catootje.2_04_11|ɹ|uː|1
Catootje.2_04_11|ɹ|ŭ|1
Catootje.2_04_11|ɹ|ɪ̆|1
Catootje.2_04_25|l|w|2
Catootje.2_04_25|l|u|4
Catootje.2_04_25|ɹ|ɯ̆|1
Catootje.2_04_25|ɹ|ŭ|1
Catootje.2_04_25|ɹ|o͡ɯ̆|1
Catootje.2_04_25|ɹ|ɔ|1
Catootje.2_05_08|l|u|3
Catootje.2_05_08|l|o|1
Catootje.2_05_08|l|ɔ|1
Catootje.2_05_08|ɹ|ɯ|3
Catootje.2_05_08|ɹ|u|1
Catootje.2_05_08|ɹ|ŭ|2
Catootje.2_05_08|ɹ|ɪ̆|1
Catootje.2_05_08|ɹ|ɤ|4
Catootje.2_05_08|ɹ|o|2
Catootje.2_05_08|ɹ|ŏ|1
Catootje.2_05_22|l|u|1
Catootje.2_05_22|l|ŭ|3
Catootje.2_05_22|ɹ|u|3
Catootje.2_05_22|ɹ|uː|1
Catootje.2_05_22|ɹ|uˑ|1
Catootje.2_05_22|ɹ|ŭ|3
Catootje.2_05_22|ɹ|ŭː|1
Catootje.2_05_22|ɹ|ɤ|6
Catootje.2_05_22|ɹ|o|1
Catootje.2_05_22|ɹ|ŏ|1
Catootje.2_06_06|l|u|3
Catootje.2_06_06|l|uː|1
Catootje.2_06_06|l|ŭ|1
Catootje.2_06_06|ɹ|j|1
Catootje.2_06_06|ɹ|ɯ|2
Catootje.2_06_06|ɹ|ɯ̆|1
Catootje.2_06_06|ɹ|u|5
Catootje.2_06_06|ɹ|ŭ|2
Catootje.2_06_06|ɹ|o|1
Catootje.2_07_04|l|u|1
Catootje.2_07_04|l|ŭ|1
Catootje.2_07_04|ɹ|u|2
Catootje.2_07_04|ɹ|ŭ|2
Catootje.2_07_04|ɹ|o|1
Catootje.2_07_04|ɹ|ə|1
Catootje.2_07_04|ɹ|ɑ|1
</opqry:message>
                </opqry:info>
                <opqry:node ref="ff2dad4523a741d7">
                    <opqry:info format="html" title="Query : Phones">
                        <opqry:message/>
                    </opqry:info>
                </opqry:node>
                <opqry:node ref="c3e1b1b7adfa4869">
                    <opqry:info format="html" title="Inventory">
                        <opqry:message/>
                    </opqry:info>
                </opqry:node>
                <opqry:node ref="f9b278a9bbba4846">
                    <opqry:info format="html" title="Sort">
                        <opqry:message/>
                    </opqry:info>
                </opqry:node>
                <opqry:optionalNode enabled="true" ref="95ceb695482449a9"/>
            </opqry:nodewizard>
            <nes:settings type="ca.phon.app.opgraph.analysis.AnalysisOpGraphEditorModel"/>
        </extensions>
    </graph>
</opgraph>
