<?xml version="1.0" encoding="UTF-8"?>
<!DOCTYPE task PUBLIC "-//OASIS//DTD DITA Task//EN" "http://docs.oasis-open.org/dita/v1.1/OS/dtd/task.dtd">
<task id="taskId">
    <title>Open Project</title>
    <shortdesc>Open an existing <i>Phon</i> project.</shortdesc>
    <taskbody>
        <context>From the <wintitle>Workspace</wintitle> window:</context>
        <steps>
            <step>
                <cmd>If the project is in your current workspace folder, click on it in the
                        <wintitle>Project List</wintitle>, or right-click
                        (<userinput>CMD/CTRL+click</userinput>) and choose <uicontrol>Open
                        project</uicontrol> from the context menu. If the project is not in your
                    current workspace folder, click the <uicontrol>Browse for Project</uicontrol>
                    button in the <wintitle>Other Actions</wintitle> pane, locate the project using
                    the resulting dialog and click <uicontrol>Open</uicontrol>.</cmd>
                <stepresult>The <wintitle>Project Manager</wintitle> window will appear.<note>If the
                        project was created using an earlier version of <i>Phon</i> (and is a
                            <i>.phon</i> or <i>.zip</i> file), you must extract the project before
                        you can open it (see <xref href="ExtractProject.xml"/> for
                        instructions).</note></stepresult>
            </step>
        </steps>
    </taskbody>
</task>
