<?xml version="1.0" encoding="UTF-8"?>
<!--
 Phon - An open source tool for research in phonology.
 Copyright (C) 2008-2014 The Phon Project, Memorial University <https://www.phon.ca>

 This program is free software: you can redistribute it and/or modify
 it under the terms of the GNU General Public License as published by
 the Free Software Foundation, either version 3 of the License, or
 (at your option) any later version.

 This program is distributed in the hope that it will be useful,
 but WITHOUT ANY WARRANTY; without even the implied warranty of
 MERCHANTABILITY or FITNESS FOR A PARTICULAR PURPOSE.  See the
 GNU General Public License for more details.
 
 You should have received a copy of the GNU General Public License
 along with this program.  If not, see <http://www.gnu.org/licenses/>.
-->
<SyllabifierDef xmlns="https://www.phon.ca/ns/syllabifier" xmlns:xsi="http://www.w3.org/2001/XMLSchema-instance"
    xsi:schemaLocation="https://www.phon.ca/ns/syllabifier ../../xml/xsd/syllabifier.xsd"
    name="English" language="eng">
    <SonorityScale>
        <!-- Plosive,Fricative,Affricate - 0 -->
        <SonorityClass>
            <exprs>
                <phonex>[{affricate}{stop,-nasal}{fricative}]</phonex>
            </exprs>
            <sonorityValue>0</sonorityValue>
        </SonorityClass>
        
        <!-- Nasal - 1 -->
        <SonorityClass>
            <exprs>
                <phonex>{nasal}</phonex>
            </exprs>
            <sonorityValue>1</sonorityValue>
        </SonorityClass>
        
        <!-- Liquid - 2 -->
        <SonorityClass>
            <exprs>
                <phonex>{liquid}</phonex>
            </exprs>
            <sonorityValue>2</sonorityValue>
        </SonorityClass>
        
        <!-- Glide - 3 -->
        <SonorityClass>
            <exprs>
                <phonex>{g}</phonex>
            </exprs>
            <sonorityValue>3</sonorityValue>
        </SonorityClass>
        
        <!-- Vowel - 4 -->
        <SonorityClass>
            <exprs>
                <phonex>{v}</phonex>
            </exprs>
            <sonorityValue>4</sonorityValue>
        </SonorityClass>
        
    </SonorityScale>
    
    <Stage name="MarkNuclei">
        <exprs>
            <phonex>(D=j{v})</phonex>
            <phonex>(D={v,-long}[ə{g,-stop,-fricative,-affricate,-liquid}{v,high,lax}])</phonex>
            <phonex>(N={v}:U)</phonex>
            <phonex>(N='.*[\u0329].*')</phonex>
        </exprs>
        <map>
            <set group="D" mark="Diphthong"/>
            <set group="N" mark="Nucleus"/>
        </map>
    </Stage>
    
    <Stage name="MarkOnset">
        <exprs>
            <phonex>(O=\c:U).:N</phonex>
            <phonex>.:N(O={g}:N).:N</phonex>
        </exprs>
        <map>
            <set group="O" mark="Onset"/>
        </map>
    </Stage>
    
    <Stage name="MaxOnset">
        <exprs>
            <phonex>(O={c,-strident}:U).:O:mdc("2","false")</phonex>
            <phonex>(O={strident, -anterior}:U).:O:mdc("2","false")</phonex>
        </exprs>
        <map>
            <set group="O" mark="Onset"/>
        </map>
    </Stage>
    
    <Stage name="Fix Diphthongs">
        <exprs>
            <phonex>.:-O?(G={g}:N).:N</phonex>
        </exprs>
        <map>
            <set group="G" mark="Onset"/>
        </map>
    </Stage>
    
    <Stage name="Glide Initial [j]">
        <exprs>
            <phonex>$(O=j:N)</phonex>
        </exprs>
        <map>
            <set group="O" mark="Onset"/>
        </map>
    </Stage>
    
    <Stage name="MarkCoda">
        <exprs>
            <phonex>.:N(C=\c:U)</phonex>
        </exprs>
        <map>
            <set group="C" mark="Coda"/>
        </map>
    </Stage>
    
    <Stage name="MaxCoda">
        <exprs>
            <phonex>.:C(C=\c:U):mdc("-1","false")</phonex>
        </exprs>
        <map>
            <set group="C" mark="Coda"/>
        </map>
    </Stage>
    
    <Stage name="Fix Branching Codas">
        <exprs>
            <phonex>.:N(C={obs,-cor}:U)</phonex>
        </exprs>
        <map>
            <set group="C" mark="Coda"/>
        </map>
    </Stage>
    
    <Stage name="MarkLA">
        <exprs>
            <phonex>$(LA={anterior,strident,voiceless}:U)</phonex>
            <phonex>.:sctype("Coda|SyllableStressMarker|SyllableBoundaryMarker|Nucleus")(LA={anterior,strident,voiceless}:U).:O</phonex>
        </exprs>
        <map>
            <set group="LA" mark="Left Appendix"/>
        </map>
    </Stage>
    
    <Stage name="MarkRA">
        <exprs>
            <phonex>.:C(RA={cor}:U)</phonex>
        </exprs>
        <map>
            <set group="RA" mark="Right Appendix"/>
        </map>
    </Stage>
    
    <Stage name="MaxRA">
        <exprs>
            <phonex>.:R(RA={c}:U+)</phonex>
        </exprs>
        <map>
            <set group="RA" mark="Right Appendix"/>
        </map>
    </Stage>
    
    <Stage name="MarkOEHS">
        <exprs>
            <phonex>(O=\c:U)</phonex>
        </exprs>
        <map>
            <set group="O" mark="OEHS"/>
        </map>
    </Stage>
    
</SyllabifierDef>
